eazyml/__init__.py
eazyml/activations.py
eazyml/layer.py
eazyml/model.py
eazyml/propagate.py
EazyML-0.1.0.dist-info/METADATA
EazyML-0.1.0.dist-info/WHEEL
EazyML-0.1.0.dist-info/top_level.txt
EazyML-0.1.0.dist-info/RECORD
