Metadata-Version: 2.1
Name: EazyML
Version: 0.1.0
Summary: Simple ML library
Home-page: https://eazyml.readthedocs.io/
Author: Joshua Geddes
Author-email: joshuageddes333@gmail.com
License: MIT
Platform: UNKNOWN
Classifier: Intended Audience :: Developers
Classifier: License :: OSI Approved :: MIT License
Classifier: Programming Language :: Python
Classifier: Programming Language :: Python :: 3.9
Classifier: Operating System :: OS Independent
Requires-Dist: numpy
